bitches/__init__.py
bitches-0.0.2.dist-info/METADATA
bitches-0.0.2.dist-info/WHEEL
bitches-0.0.2.dist-info/top_level.txt
bitches-0.0.2.dist-info/RECORD
