Metadata-Version: 2.1
Name: bitches
Version: 0.0.2
Summary: how about you pip install some bitches
Home-page: https://github.com/rdimo/pip-install-bitches
Author: Rdimo
Author-email: <contact.rdimo@gmail.com>
License: UNKNOWN
Project-URL: Bug Tracker, https://github.com/rdimo/pip-install-bitches/issues
Keywords: bitches,python,package,library,lib,module,checker
Platform: UNKNOWN
Classifier: Intended Audience :: Developers
Classifier: Programming Language :: Python :: 3
Classifier: License :: OSI Approved :: MIT License
Classifier: Operating System :: OS Independent
Requires-Dist: requests
